app/__init__.py
app/api/__init__.py
app/api/assistants.py
app/api/runs.py
app/api/threads.py
app/chain.py
app/cli.py
app/docker-compose-cli.yml
app/examples/message_graph.py
app/examples/state_graph.py
app/hack.py
app/lib/__init__.py
app/lib/agent.py
app/lib/checkpoint.py
app/lib/ingest.py
app/lib/lifespan.py
app/lib/message_types.py
app/lib/parsing.py
app/lib/schema.py
app/lib/storage.py
app/lib/stream.py
app/lib/upload.py
app/migrations/000001_create_extensions_and_first_tables.down.sql
app/migrations/000001_create_extensions_and_first_tables.up.sql
app/migrations/000002_checkpoints_update_schema.down.sql
app/migrations/000002_checkpoints_update_schema.up.sql
app/server.py
langgraph_studio-0.0.4.dist-info/METADATA
langgraph_studio-0.0.4.dist-info/WHEEL
langgraph_studio-0.0.4.dist-info/entry_points.txt
langgraph_studio-0.0.4.dist-info/RECORD
