Metadata-Version: 2.1
Name: langgraph-studio
Version: 0.0.4
Summary: 
Author: LangChain
Author-email: nuno@langchain.dev
Requires-Python: >=3.9.0,<3.12
Classifier: Programming Language :: Python :: 3
Classifier: Programming Language :: Python :: 3.9
Classifier: Programming Language :: Python :: 3.10
Classifier: Programming Language :: Python :: 3.11
Requires-Dist: anthropic (>=0.13.0,<0.14.0)
Requires-Dist: arxiv (>=2.1.0,<3.0.0)
Requires-Dist: asyncpg (>=0.29.0,<0.30.0)
Requires-Dist: beautifulsoup4 (>=4.12.3,<5.0.0)
Requires-Dist: boto3 (>=1.34.28,<2.0.0)
Requires-Dist: duckduckgo-search (>=4.2,<5.0)
Requires-Dist: fastapi (>=0.103.2,<0.104.0)
Requires-Dist: fireworks-ai (>=0.11.2,<0.12.0)
Requires-Dist: httpx[socks] (==0.25.2)
Requires-Dist: kay (>=0.1.2,<0.2.0)
Requires-Dist: langchain (>=0.0.338)
Requires-Dist: langchain-core (>=0.1.33,<0.2.0)
Requires-Dist: langchain-google-vertexai (>=0.0.3,<0.0.4)
Requires-Dist: langchain-openai (>=0.0.8,<0.0.9)
Requires-Dist: langchain-robocorp (>=0.0.4,<0.0.5)
Requires-Dist: langgraph (>=0.0.29,<0.0.30)
Requires-Dist: langserve (==0.0.32)
Requires-Dist: orjson (>=3.9.10,<4.0.0)
Requires-Dist: pdfminer-six (>=20231228,<20231229)
Requires-Dist: pgvector (>=0.2.5,<0.3.0)
Requires-Dist: psycopg2-binary (>=2.9.9,<3.0.0)
Requires-Dist: pydantic (<2.0)
Requires-Dist: python-magic (>=0.4.27,<0.5.0)
Requires-Dist: python-multipart (>=0.0.6,<0.0.7)
Requires-Dist: setuptools (>=69.0.3,<70.0.0)
Requires-Dist: sse-starlette (>=1.6.5,<2.0.0)
Requires-Dist: tiktoken (>=0.5.1,<0.6.0)
Requires-Dist: tomli-w (>=1.0.0,<2.0.0)
Requires-Dist: unstructured[doc,docx] (>=0.12.5,<0.13.0)
Requires-Dist: uvicorn (>=0.23.2,<0.24.0)
Requires-Dist: wikipedia (>=1.4.0,<2.0.0)
Requires-Dist: xmltodict (>=0.13.0,<0.14.0)
